<?xml version="1.0" encoding="UTF-8"?>
<typeOfXMLFile encodingDescription="byzMusicXML" version="1.0">
	<head>
		<!--meta-->
		<nameFile>gr_iviron1167_53r_1</nameFile>

		<!--manuscript-->
		<library>iviron</library>
		<libraryΝumber>1167</libraryΝumber>
		<catalogue>stathes gregorios 2015:470-471</catalogue>
		
		<!--musicPiece-->
		<startingFolio>53r</startingFolio>
		<initium>εβοησε σοι ιδων ο πρεσβυς</initium>
		<mode>3</mode>
		<kind>heirmos</kind>
		<numLine>1</numLine>
		<startingPitch>c</startingPitch>
		<composer>theophanes karykes</composer>

		<!--languageAndAlphabet-->
		<lyricsLang>greek</lyricsLang>
		<alphabet>greek</alphabet>

		<!--moreDetails-->
		<moreDetails/>
		<orthography>recension</orthography>
	</head>
	<musicalPiece>
echos_c i, i = c- #διόρθωση
i = ε
p klr = βό
ae2 = η
oo kl para_ 1 vv 1 = σέ|
ae2 para_ vv = σοι|-
echos_a aa = a-
i = ι
o = δών|
o = ο|
o dd is g, oo g = πρέ
i = σβυς|
i = τοις|
i = ο
i is g = φθαλ
pi klr = μοίς|
ae2 = το|
i = σω
p klr , a = τή
a kl para_ 1= ρι
aa para_ = ον|-
ph4 = ο|
ae2 = λα
o kr = οίς|
ae2 = ε
p = πέ
ae2 = στη|
ooh4 = εκ|
i = θε
ook2 psr = ού|
a is g = χρι
a = στέ|
pi l 1 = συ|
ae2 l = θε
p klr = ός|
a ap = μου|
</musicalPiece>
</typeOfXMLFile>