<?xml version="1.0" encoding="UTF-8"?>
<typeOfXMLFile encodingDescription="byzMusicXML" version="1.0">
	<head>
		<!--meta-->
		<nameFile>gr_iviron1167_110v_2</nameFile>

		<!--manuscript-->
		<library>iviron</library>
		<libraryΝumber>1167</libraryΝumber>
		<catalogue>stathes gregorios 2015:470-471</catalogue>
		
		<!--musicPiece-->
		<startingFolio>110v</startingFolio>
		<initium>ασπορου τοκου συλληψιν</initium>
		<mode>7</mode>
		<kind>heirmos</kind>
		<numLine>1</numLine>
		<startingPitch>F</startingPitch>
		<composer>theophanes karykes</composer>

		<!--languageAndAlphabet-->
		<lyricsLang>greek</lyricsLang>
		<alphabet>greek</alphabet>

		<!--moreDetails-->
		<moreDetails/>
		<orthography>recension</orthography>
	</head>
	<musicalPiece>
echos_varys o dd = F -
i = α
ok2 = σπό
i = ρου|
i = τό
i = κου|
oo psr = σύλ
a klr 1 = λη
aa klr = ψιν|-
a anr 1 = τις
a anr kl = ερ
a = μη
ok2 = νεύ
pi = σει|
ae2 = γη
o g = γε
o ap = νών|-
i = α
ok2 is g = φθό
i = ρου|
i = τό
i = κου|
oo psr = γέν
a klr = νη
a anr 1 = σιν|-
a anr klr = τις|
a = μη|
a = θαυ
po klr = μά
ae2 = σει|
o is g = βρο
o ap = τών|-
i = δι
ok2 = ό|
i = σε|
i klr = αι|
i = φυ
i = λαί|
oo psr = πά
a klr = σαι|
a = της|
i ap = γης|-
ae2 = θε
ok2 = ο
ooi psr = τό
a = κε|
a anr klr = με
a = γα
kkoo z = λύ
ae2, kk g = νο
o ap = μεν|
</musicalPiece>
</typeOfXMLFile>