<?xml version="1.0" encoding="UTF-8"?>
<typeOfXMLFile encodingDescription="byzMusicXML" version="1.0">
	<head>
		<!--meta-->
		<nameFile>gr_iviron1167_67r_2</nameFile>

		<!--manuscript-->
		<library>iviron</library>
		<libraryΝumber>1167</libraryΝumber>
		<catalogue>stathes gregorios 2015:470-471</catalogue>
		
		<!--musicPiece-->
		<startingFolio>67r</startingFolio>
		<initium>την θειαν ταυτην και παντιμον τελουντες εορτην</initium>
		<mode>4</mode>
		<kind>heirmos</kind>
		<numLine>1</numLine>
		<startingPitch>b</startingPitch>
		<composer>theophanes karykes</composer>

		<!--languageAndAlphabet-->
		<lyricsLang>greek</lyricsLang>
		<alphabet>greek</alphabet>

		<!--moreDetails-->
		<moreDetails/>
		<orthography>recension</orthography>
	</head>
	<musicalPiece>
echos_b aa, kkoo = b -
i = την|
ok2 = θεί
i = αν|
p klr = ταυ
aa = την|
i = καί|
ooi psr = πά
a kl = ντι
ae2 = μον|-
i = τε
ook3 = λού
pi = ντες|
ae2 = έ
o g = ορ
o ap = τήν|-
i = οί|
i = θε
ooi psr = ό
a kl = φρο
ae2 = νες|
o = τής|
p anr 1 = θε
a anr = ο
ook2 psr = μή
a kl = το
ae2 = ρος|-
ok3 = δεύ
i = τε|
i = τάς|
p anr = χεί
a = ρας|
i is g = κρο
ooi psr = τή
a klr = σω
ae2 = μεν|-
i = τον|
o = εξ|
o = αυ
p anr ddr = τής|
ae3 = τε
o is g, p l 1= χθέ
ae2 l = ντα|
o = θε
o = ον|
o = δο
ooi psr = ξά
a klr = ζο
aa ap = ντες|
</musicalPiece>
</typeOfXMLFile>