<?xml version="1.0" encoding="UTF-8"?>
<typeOfXMLFile encodingDescription="byzMusicXML" version="1.0">
	<head>
		<!--meta-->
		<nameFile>gr_iviron1101_81r_2</nameFile>

		<!--manuscript-->
		<library>iviron</library>
		<libraryΝumber>1101</libraryΝumber>
		<catalogue>Chaldaiakis 2015:175-208</catalogue>
		
		<!--musicPiece-->
		<startingFolio>81r</startingFolio>
		<initium>ο στερεωσας καταρχας τους ουρανους εν συνεσει</initium>
		<mode>8</mode>
		<kind>heirmos</kind>
		<numLine>1</numLine>
		<startingPitch>c</startingPitch>
		<composer>Αnonymous</composer>

		<!--languageAndAlphabet-->
		<lyricsLang>greek</lyricsLang>
		<alphabet>greek</alphabet>

		<!--moreDetails-->
		<moreDetails/>
		<orthography>recension</orthography>
	</head>
	<musicalPiece>
echos_pld ok3, i dd = c -
i = ο|
i = στε
p = ρε
a = ώ
a kl = σας|
a = κα
k v 1, a v = ταρ
o ap = χάς|-
o = τους|
i = ου
i = ρα
pi = νούς|
a kl 1 di 1, a kl di = εν|
a = συ
k v 1, a v = νέ
o dd, oo = σει|-
i = και|
i = την|
ooi = γήν|
a = ε
a kl = πι|
a = υ
o = δά
p = των|
ae2 = ε
k v 1, a v = δρά
o dd, oo = σας|-
i = εν|
i = τη|
pi = πέ
a kl 1 di 1, a kl di = τρα|
a = με|
okk = χρι
o ap = στέ|-
i = των|
pi = ε
ae3 = ντο
okk = λών|
p = σου|
a = στή
a kl = ρι
a = ξον|-
i = ό
i = τι|
p = ουκ|
a kl = έ
ae3, kk = στι|
o dd, oo = πλήν|
i dd = σου|-
ooh4 = ά
a = γι
ae2, kk = ος|
oo = μό
a = νε|
a = φι
po = λάν
ae3 = θρω
o ap = πε|
</musicalPiece>
</typeOfXMLFile>